{"is_source_file": false, "format": "", "description": "", "external_files": [], "external_methods": [], "published": [], "classes": [], "methods": [], "calls": [], "search-terms": [], "state": 2, "file_id": 1, "knowledge_revision": 24, "git_revision": "df3ac2d22cfcd05ed9c1d7a33211808696d41756", "hash": "5110d5b39a28d12a4711ccc7ba1d4ac1", "format-version": 4, "code-base-name": "products_backend_api", "filename": "README.md", "revision_history": [{"24": "df3ac2d22cfcd05ed9c1d7a33211808696d41756"}]}